cutshort/__init__.py
cutshort/core.py
cutshort-0.0.4.dist-info/LICENSE.txt
cutshort-0.0.4.dist-info/METADATA
cutshort-0.0.4.dist-info/WHEEL
cutshort-0.0.4.dist-info/top_level.txt
cutshort-0.0.4.dist-info/RECORD
